biliget/__init__.py
biliget/basics.py
biliget/fun.py
biliget/ob.py
biliget-1.3.7.dist-info/LICENSE
biliget-1.3.7.dist-info/METADATA
biliget-1.3.7.dist-info/WHEEL
biliget-1.3.7.dist-info/top_level.txt
biliget-1.3.7.dist-info/RECORD
