Metadata-Version: 2.1
Name: biliget
Version: 1.3.7
Summary: Help with bilibili.
Home-page: https://github.com/lixiaobai468/biliget
Author: lixiaobai
Author-email: 18108274905@163.com
License: UNKNOWN
Platform: UNKNOWN
Classifier: Programming Language :: Python :: 3
Classifier: License :: OSI Approved :: MIT License
Classifier: Operating System :: OS Independent
Requires-Dist: requests
Requires-Dist: matplotlib
